README.rst
setup.py
heconvert/__init__.py
heconvert/converter.py
heconvert/core.py
heconvert.egg-info/PKG-INFO
heconvert.egg-info/SOURCES.txt
heconvert.egg-info/dependency_links.txt
heconvert.egg-info/top_level.txt
heconvert/keyboard/__init__.py
heconvert/keyboard/ksx5002/__init__.py
heconvert/keyboard/ksx5002/core.py
heconvert/keyboard/ksx5002/interface.py
heconvert/keyboard/ksx5002/mapping.py
heconvert/misc/__init__.py
heconvert/misc/util.py
test/__init__.py
test/tests.py