Metadata-Version: 1.1
Name: heconvert
Version: 1.0.2
Summary: simple converter that converts hangul to english and vise versa
Home-page: https://github.com/makerj/heconvert
Author: makerj
Author-email: ohenwkgdj@gmail.com
License:                               Apache License
